ctfd_downloader/__init__.py
ctfd_downloader/format.py
ctfd_downloader/main.py
ctfd_downloader-1.0.1.dist-info/licenses/LICENSE
ctfd_downloader-1.0.1.dist-info/METADATA
ctfd_downloader-1.0.1.dist-info/WHEEL
ctfd_downloader-1.0.1.dist-info/entry_points.txt
ctfd_downloader-1.0.1.dist-info/top_level.txt
ctfd_downloader-1.0.1.dist-info/RECORD
