Metadata-Version: 2.4
Name: ctfd_downloader
Version: 1.0.1
Summary: A tool to download challenges, files, and metadata from a CTFd instance and output them into an organized directory.
Author: Jacob Elliott
Author-email: coachelliott@uscybergames.org
Classifier: Programming Language :: Python :: 3
Classifier: Operating System :: OS Independent
Requires-Python: >=3.6
License-File: LICENSE
Requires-Dist: requests>=2.32.0
Requires-Dist: slugify>=0.0.1
Requires-Dist: tqdm>=4.66.3
Dynamic: author
Dynamic: author-email
Dynamic: classifier
Dynamic: description
Dynamic: description-content-type
Dynamic: license-file
Dynamic: requires-dist
Dynamic: requires-python
Dynamic: summary
